pytzen/__init__.py
pytzen/config/__init__.py
pytzen/config/yaml.py
pytzen/data/__init__.py
pytzen/data/pipeline.py
pytzen-1.1.6.dist-info/LICENSE
pytzen-1.1.6.dist-info/METADATA
pytzen-1.1.6.dist-info/WHEEL
pytzen-1.1.6.dist-info/top_level.txt
pytzen-1.1.6.dist-info/RECORD
