Metadata-Version: 2.1
Name: pytzen
Version: 1.1.6
Summary: DATA LAB
Home-page: https://pytzen.com
Author: PYTZEN
Classifier: Programming Language :: Python :: 3
Classifier: License :: OSI Approved :: MIT License
Classifier: Operating System :: OS Independent
Requires-Python: >=3.10
License-File: LICENSE
